zalando_cli_bundle/__main__.py
zalando_cli_bundle/cli.py
zalando_cli_bundle-24.19.2.dist-info/METADATA
zalando_cli_bundle-24.19.2.dist-info/WHEEL
zalando_cli_bundle-24.19.2.dist-info/entry_points.txt
zalando_cli_bundle-24.19.2.dist-info/RECORD
