Metadata-Version: 2.4
Name: zalando-cli-bundle
Version: 24.19.2
Summary: CLI bundle for Zalando developers
Author: Henning Jacobs
Author-email: henning@zalando.de
Requires-Python: >=3.9,<4.0
Classifier: Environment :: Console
Classifier: Framework :: Pytest
Classifier: Intended Audience :: Developers
Classifier: Intended Audience :: System Administrators
Classifier: Operating System :: POSIX :: Linux
Classifier: Programming Language :: Python
Classifier: Programming Language :: Python :: 3
Classifier: Programming Language :: Python :: 3.9
Classifier: Programming Language :: Python :: 3.10
Classifier: Programming Language :: Python :: 3.11
Classifier: Programming Language :: Python :: 3.12
Classifier: Programming Language :: Python :: 3.13
Classifier: Programming Language :: Python :: 3.14
Classifier: Programming Language :: Python :: Implementation :: CPython
Requires-Dist: click (>=7.1.2,<8.0.0)
Requires-Dist: stups-cli-support (>=1.1.22,<2.0.0)
Requires-Dist: stups-kio (>=0.1.25,<0.2.0)
Requires-Dist: stups-pierone (>=1.1.53,<2.0.0)
Requires-Dist: stups-zign (>=1.2,<2.0)
Requires-Dist: zalando-kubectl (>=1.31.1.237,<2.0.0.0)
Project-URL: Repository, https://github.com/zalando-build/zalando-cli-bundle
